pytest_unordered/__init__.py
pytest_unordered/py.typed
pytest_unordered-0.7.0.dist-info/licenses/LICENSE
pytest_unordered-0.7.0.dist-info/METADATA
pytest_unordered-0.7.0.dist-info/WHEEL
pytest_unordered-0.7.0.dist-info/entry_points.txt
pytest_unordered-0.7.0.dist-info/top_level.txt
pytest_unordered-0.7.0.dist-info/RECORD
